<?xml version="1.0" encoding="UTF-8" ?>
<persistence xmlns="http://xmlns.jcp.org/xml/ns/persistence" version="2.1">

    <persistence-unit name="manyToMany" transaction-type="RESOURCE_LOCAL">

        <provider>org.hibernate.jpa.HibernatePersistenceProvider</provider>

        <class>org.academia.persistence.jpa.associations.many2many.User</class>
        <class>org.academia.persistence.jpa.associations.many2many.SecurityGroup</class>

        <properties>
            <property name="javax.persistence.jdbc.driver" value="org.postgresql.Driver"/>
            <property name="javax.persistence.jdbc.url" value="jdbc:postgresql://localhost:5432/jpa"/>
            <property name="javax.persistence.jdbc.user" value="postgres"/>
            <property name="javax.persistence.jdbc.password" value=""/>
            <property name="hibernate.dialect" value="org.hibernate.dialect.PostgreSQL9Dialect"/>
            <!-- this property tells hibernate what to scan for annotation,
            no value means it will only look at the classes defined above -->
            <property name="hibernate.archive.autodetection" value=""/>
            <property name="hibernate.show_sql" value="false"/>
            <property name="hibernate.format_sql" value="true"/>
            <property name="hibernate.hbm2ddl.auto" value="create"/>
        </properties>
    </persistence-unit>

    <persistence-unit name="manyToOne" transaction-type="RESOURCE_LOCAL">

        <provider>org.hibernate.jpa.HibernatePersistenceProvider</provider>

        <class>org.academia.persistence.jpa.associations.many2one.Category</class>
        <class>org.academia.persistence.jpa.associations.many2one.Product</class>

        <properties>
            <property name="javax.persistence.jdbc.driver" value="org.postgresql.Driver"/>
            <property name="javax.persistence.jdbc.url" value="jdbc:postgresql://localhost:5432/jpa"/>
            <property name="javax.persistence.jdbc.user" value="postgres"/>
            <property name="javax.persistence.jdbc.password" value=""/>
            <property name="hibernate.dialect" value="org.hibernate.dialect.PostgreSQL9Dialect"/>
            <!-- this property tells hibernate what to scan for annotation,
            no value means it will only look at the classes defined above -->
            <property name="hibernate.archive.autodetection" value=""/>
            <property name="hibernate.show_sql" value="false"/>
            <property name="hibernate.format_sql" value="true"/>
            <property name="hibernate.hbm2ddl.auto" value="create"/>
        </properties>
    </persistence-unit>

    <persistence-unit name="oneToOne" transaction-type="RESOURCE_LOCAL">

        <provider>org.hibernate.jpa.HibernatePersistenceProvider</provider>

        <class>org.academia.persistence.jpa.associations.one2one.Car</class>
        <class>org.academia.persistence.jpa.associations.one2one.Owner</class>


        <properties>
            <property name="javax.persistence.jdbc.driver" value="org.postgresql.Driver"/>
            <property name="javax.persistence.jdbc.url" value="jdbc:postgresql://localhost:5432/jpa"/>
            <property name="javax.persistence.jdbc.user" value="postgres"/>
            <property name="javax.persistence.jdbc.password" value=""/>
            <property name="hibernate.dialect" value="org.hibernate.dialect.PostgreSQL9Dialect"/>
            <!-- this property tells hibernate what to scan for annotation,
            no value means it will only look at the classes defined above -->
            <property name="hibernate.archive.autodetection" value=""/>
            <property name="hibernate.show_sql" value="false"/>
            <property name="hibernate.format_sql" value="true"/>
            <property name="hibernate.hbm2ddl.auto" value="create"/>
        </properties>
    </persistence-unit>

    <persistence-unit name="component" transaction-type="RESOURCE_LOCAL">

        <provider>org.hibernate.jpa.HibernatePersistenceProvider</provider>

        <class>org.academia.persistence.jpa.component.Address</class>
        <class>org.academia.persistence.jpa.component.Student</class>

        <properties>
            <property name="javax.persistence.jdbc.driver" value="org.postgresql.Driver"/>
            <property name="javax.persistence.jdbc.url" value="jdbc:postgresql://localhost:5432/jpa"/>
            <property name="javax.persistence.jdbc.user" value="postgres"/>
            <property name="javax.persistence.jdbc.password" value=""/>
            <property name="hibernate.dialect" value="org.hibernate.dialect.PostgreSQL9Dialect"/>
            <!-- this property tells hibernate what to scan for annotation,
            no value means it will only look at the classes defined above -->
            <property name="hibernate.archive.autodetection" value=""/>
            <property name="hibernate.show_sql" value="true"/>
            <property name="hibernate.format_sql" value="true"/>
            <property name="hibernate.hbm2ddl.auto" value="create"/>
        </properties>
    </persistence-unit>

    <persistence-unit name="entity" transaction-type="RESOURCE_LOCAL">

        <provider>org.hibernate.jpa.HibernatePersistenceProvider</provider>

        <class>org.academia.persistence.jpa.entity.User</class>

        <properties>
            <property name="javax.persistence.jdbc.driver" value="org.postgresql.Driver"/>
            <property name="javax.persistence.jdbc.url" value="jdbc:postgresql://localhost:5432/jpa"/>
            <property name="javax.persistence.jdbc.user" value="postgres"/>
            <property name="javax.persistence.jdbc.password" value=""/>
            <property name="hibernate.dialect" value="org.hibernate.dialect.PostgreSQL9Dialect"/>
            <!-- this property tells hibernate what to scan for annotation,
            no value means it will only look at the classes defined above -->
            <property name="hibernate.archive.autodetection" value=""/>
            <property name="hibernate.show_sql" value="true"/>
            <property name="hibernate.format_sql" value="true"/>
            <property name="hibernate.hbm2ddl.auto" value="create"/>
        </properties>
    </persistence-unit>

    <persistence-unit name="joinedTable" transaction-type="RESOURCE_LOCAL">

        <provider>org.hibernate.jpa.HibernatePersistenceProvider</provider>

        <class>org.academia.persistence.jpa.inheritance.joined_table.Boat</class>
        <class>org.academia.persistence.jpa.inheritance.joined_table.Car</class>
        <class>org.academia.persistence.jpa.inheritance.joined_table.Vehicle</class>

        <properties>
            <property name="javax.persistence.jdbc.driver" value="org.postgresql.Driver"/>
            <property name="javax.persistence.jdbc.url" value="jdbc:postgresql://localhost:5432/jpa"/>
            <property name="javax.persistence.jdbc.user" value="postgres"/>
            <property name="javax.persistence.jdbc.password" value=""/>
            <property name="hibernate.dialect" value="org.hibernate.dialect.PostgreSQL9Dialect"/>
            <!-- this property tells hibernate what to scan for annotation,
            no value means it will only look at the classes defined above -->
            <property name="hibernate.archive.autodetection" value=""/>
            <property name="hibernate.show_sql" value="true"/>
            <property name="hibernate.format_sql" value="true"/>
            <property name="hibernate.hbm2ddl.auto" value="create"/>
        </properties>
    </persistence-unit>

    <persistence-unit name="singleTable" transaction-type="RESOURCE_LOCAL">

        <provider>org.hibernate.jpa.HibernatePersistenceProvider</provider>

        <class>org.academia.persistence.jpa.inheritance.single_table.Boat</class>
        <class>org.academia.persistence.jpa.inheritance.single_table.Car</class>
        <class>org.academia.persistence.jpa.inheritance.single_table.Vehicle</class>

        <properties>
            <property name="javax.persistence.jdbc.driver" value="org.postgresql.Driver"/>
            <property name="javax.persistence.jdbc.url" value="jdbc:postgresql://localhost:5432/jpa"/>
            <property name="javax.persistence.jdbc.user" value="postgres"/>
            <property name="javax.persistence.jdbc.password" value=""/>
            <property name="hibernate.dialect" value="org.hibernate.dialect.PostgreSQL9Dialect"/>
            <!-- this property tells hibernate what to scan for annotation,
            no value means it will only look at the classes defined above -->
            <property name="hibernate.archive.autodetection" value=""/>
            <property name="hibernate.show_sql" value="true"/>
            <property name="hibernate.format_sql" value="true"/>
            <property name="hibernate.hbm2ddl.auto" value="create"/>
        </properties>
    </persistence-unit>

    <persistence-unit name="tablePerClass" transaction-type="RESOURCE_LOCAL">

        <provider>org.hibernate.jpa.HibernatePersistenceProvider</provider>

        <class>org.academia.persistence.jpa.inheritance.table_per_class.Boat</class>
        <class>org.academia.persistence.jpa.inheritance.table_per_class.Car</class>
        <class>org.academia.persistence.jpa.inheritance.table_per_class.Vehicle</class>

        <properties>
            <property name="javax.persistence.jdbc.driver" value="org.postgresql.Driver"/>
            <property name="javax.persistence.jdbc.url" value="jdbc:postgresql://localhost:5432/jpa"/>
            <property name="javax.persistence.jdbc.user" value="postgres"/>
            <property name="javax.persistence.jdbc.password" value=""/>
            <property name="hibernate.dialect" value="org.hibernate.dialect.PostgreSQL9Dialect"/>
            <!-- this property tells hibernate what to scan for annotation,
            no value means it will only look at the classes defined above -->
            <property name="hibernate.archive.autodetection" value=""/>
            <property name="hibernate.show_sql" value="false"/>
            <property name="hibernate.format_sql" value="true"/>
            <property name="hibernate.hbm2ddl.auto" value="create"/>
        </properties>
    </persistence-unit>

    <persistence-unit name="mappedSuperClass" transaction-type="RESOURCE_LOCAL">

        <provider>org.hibernate.jpa.HibernatePersistenceProvider</provider>

        <class>org.academia.persistence.jpa.inheritance.mapped_superclass.Customer</class>
        <class>org.academia.persistence.jpa.inheritance.mapped_superclass.Account</class>
        <class>org.academia.persistence.jpa.inheritance.mapped_superclass.AbstractModel</class>

        <properties>
            <property name="javax.persistence.jdbc.driver" value="org.postgresql.Driver"/>
            <property name="javax.persistence.jdbc.url" value="jdbc:postgresql://localhost:5432/jpa"/>
            <property name="javax.persistence.jdbc.user" value="postgres"/>
            <property name="javax.persistence.jdbc.password" value=""/>
            <property name="hibernate.dialect" value="org.hibernate.dialect.PostgreSQL9Dialect"/>
            <!-- this property tells hibernate what to scan for annotation,
            no value means it will only look at the classes defined above -->
            <property name="hibernate.archive.autodetection" value=""/>
            <property name="hibernate.show_sql" value="true"/>
            <property name="hibernate.format_sql" value="true"/>
            <property name="hibernate.hbm2ddl.auto" value="create"/>
        </properties>
    </persistence-unit>

    <persistence-unit name="test" transaction-type="RESOURCE_LOCAL">

        <provider>org.hibernate.jpa.HibernatePersistenceProvider</provider>

        <class>org.academia.persistence.jpa.Main</class>

        <properties>
            <property name="javax.persistence.jdbc.driver" value="org.postgresql.Driver"/>
            <property name="javax.persistence.jdbc.url" value="jdbc:postgresql://localhost:5432/jpa"/>
            <property name="javax.persistence.jdbc.user" value="postgres"/>
            <property name="javax.persistence.jdbc.password" value=""/>
            <property name="hibernate.dialect" value="org.hibernate.dialect.PostgreSQL9Dialect"/>
            <property name="hibernate.archive.autodetection" value=""/>
            <property name="hibernate.show_sql" value="true"/>
            <property name="hibernate.format_sql" value="true"/>
            <property name="hibernate.hbm2ddl.auto" value="create"/>
        </properties>

    </persistence-unit>

</persistence>
